mycol/__init__.py
mycol/numbers.py
Mycol-0.0.4.dist-info/LICENSE
Mycol-0.0.4.dist-info/METADATA
Mycol-0.0.4.dist-info/WHEEL
Mycol-0.0.4.dist-info/top_level.txt
Mycol-0.0.4.dist-info/RECORD
