Metadata-Version: 2.1
Name: Mycol
Version: 0.0.4
Summary: Collection of random functions.
Home-page: https://github.com/Mattimated/my
Author: Mattimated
Project-URL: Homepage, https://github.com/Mattimated/my
Project-URL: Bug Tracker, https://github.com/Mattimated/my/issues
Classifier: Programming Language :: Python :: 3
Classifier: License :: OSI Approved :: MIT License
Classifier: Operating System :: OS Independent
Requires-Python: >=3.7
License-File: LICENSE
